
{ "id": 10092, "name": "letter 92A", "lat": 28.9216312824212, "lon": -0.17578125, "size": 8289, "year": 408, "color": "blue", "date": "before 408", "person1": "Sender: Augustine", "loc": "", "person2": "Recipient: Cyprian", "loc2": "Rome (en route)", "Correspondent_Clerical_Rank": "Priest", "Ascetic Content": "", "Other_Personal_Names_Mentioned": "Italica", "Inferred Names": "", "Groups": "", "Literary/Historical References": "", "Other Locations Mentioned": "" }, { "id": 20092, "name": "letter 92A", "lat": 41.891775, "lon": 12.486137, "size": 8289, "year": 408, "color": "red", "date": "before 408", "person1": "Recipient: Hilary", "loc": "Rome (en route)", "person2": "Sender: Augustine", "loc2": "", "Correspondent_Clerical_Rank": "Priest", "Ascetic Content": "", "Other_Personal_Names_Mentioned": "Italica", "Inferred Names": "", "Groups": "", "Literary/Historical References": "", "Other Locations Mentioned": "" },

{ "id": 1184, "name": "letter 184", "lat": 41.891775, "lon": 12.486137, "size": 8299, "year": 415, "color": "blue", "date": "415", "person1": "Sender: Innocent", "loc": "Rome", "person2": "Recipient: Aurelius, Alypius", "loc2": "Carthage", "Correspondent_Clerical_Rank": "bishop", "Ascetic Content": "No", "Other_Personal_Names_Mentioned": "Germanus", "Inferred Names": "", "Groups": "", "Literary/Historical References": "", "Other Locations Mentioned": "" }, { "id": 2184, "name": "letter 184", "lat": 36.8500325, "lon": 10.318, "size": 8299, "year": 415, "color": "red", "date": "415", "person1": "Recipient: Innocent", "loc": "Carthage", "person2": "Sender: Innocent", "loc2": "Rome", "Correspondent_Clerical_Rank": "bishop", "Ascetic Content": "No", "Other_Personal_Names_Mentioned": "Germanus", "Inferred Names": "", "Groups": "", "Literary/Historical References": "", "Other Locations Mentioned": "" },
{ "id": 10184, "name": "letter 184A", "lat": 36.882478, "lon": 7.751272, "size": 8299, "year": 418, "color": "blue", "date": "418", "person1": "Sender: Augustine", "loc": "Hippo Regius", "person2": "Recipient: Peter and Abraham", "loc2": "", "Correspondent_Clerical_Rank": "monk", "Ascetic Content": "Yes", "Other_Personal_Names_Mentioned": "Stephen, Firmus", "Inferred Names": "Mary (Mother of Jesus); Paul; Peter and Abraham", "Groups": "", "Literary/Historical References": "scripture; Mk 16:16; Mt 10:15; Gn 1:22; Is 7:9 LXX; Rom 10:1; 1 Cor 10:20; Rom 1:25; PS 13:1; Ps 93:7", "Other Locations Mentioned": "Sodom" }, { "id": 20184, "name": "letter 184A", "lat": 28.9216312824212, "lon": -0.17578125, "size": 8299, "year": 418, "color": "red", "date": "418", "person1": "Recipient: Augustine", "loc": "", "person2": "Sender: Augustine", "loc2": "Hippo Regius", "Correspondent_Clerical_Rank": "monk", "Ascetic Content": "Yes", "Other_Personal_Names_Mentioned": "Stephen, Firmus", "Inferred Names": "Mary (Mother of Jesus); Paul; Peter and Abraham", "Groups": "", "Literary/Historical References": "scripture; Mk 16:16; Mt 10:15; Gn 1:22; Is 7:9 LXX; Rom 10:1; 1 Cor 10:20; Rom 1:25; PS 13:1; Ps 93:7", "Other Locations Mentioned": "Sodom" },
{ "id": 1185, "name": "letter 185", "lat": 36.882478, "lon": 7.751272, "size": 66773, "year": 417, "color": "blue", "date": "417", "person1": "Sender: Augustine", "loc": "Hippo Regius", "person2": "Recipient: Boniface", "loc2": "Africa", "Correspondent_Clerical_Rank": "layman", "Ascetic Content": "No", "Other_Personal_Names_Mentioned": "", "Inferred Names": "", "Groups": "", "Literary/Historical References": "", "Other Locations Mentioned": "" }, { "id": 2185, "name": "letter 185", "lat": 37.5, "lon": 7.5, "size": 66773, "year": 417, "color": "red", "date": "417", "person1": "Recipient: Augustine", "loc": "Africa", "person2": "Sender: Augustine", "loc2": "Hippo Regius", "Correspondent_Clerical_Rank": "layman", "Ascetic Content": "No", "Other_Personal_Names_Mentioned": "", "Inferred Names": "", "Groups": "", "Literary/Historical References": "", "Other Locations Mentioned": "" },
{ "id": 10185, "name": "letter 185A", "lat": 36.882478, "lon": 7.751272, "size": 66773, "year": 416, "color": "blue", "date": "N.A.", "person1": "Sender: Augustine", "loc": "Hippo Regius", "person2": "Recipient: Boniface", "loc2": "Africa", "Correspondent_Clerical_Rank": "layman", "Ascetic Content": "No", "Other_Personal_Names_Mentioned": "", "Inferred Names": "", "Groups": "", "Literary/Historical References": "", "Other Locations Mentioned": "" }, { "id": 20185, "name": "letter 185A", "lat": 37.5, "lon": 7.5, "size": 66773, "year": 416, "color": "red", "date": "N.A.", "person1": "Recipient: Augustine", "loc": "Africa", "person2": "Sender: Augustine", "loc2": "Hippo Regius", "Correspondent_Clerical_Rank": "layman", "Ascetic Content": "No", "Other_Personal_Names_Mentioned": "", "Inferred Names": "", "Groups": "", "Literary/Historical References": "", "Other Locations Mentioned": "" },
{ "id": 1186, "name": "letter 186", "lat": 36.882478, "lon": 7.751272, "size": 46518, "year": 416, "color": "blue", "date": "416", "person1": "Sender: Alypius, Augustine", "loc": "Hippo Regius", "person2": "Recipient: Paulinus", "loc2": "Nola", "Correspondent_Clerical_Rank": "bishop", "Ascetic Content": "No", "Other_Personal_Names_Mentioned": "Januarius; Pelagius \"The Briton\"; Pelagius;  Timasius; James (disciple of Pelagius); Innocent; Adam; Moses; Esau; Jacob; Pharaoh; Abraham; Timothy", "Inferred Names": "Paul; The 12 Apostles; Paulinus; David", "Groups": "Pelagians; Jews; Church of Jerusalem; ", "Literary/Historical References": "Gal 2:21; Phil 2:13; Lk 19:10; 1 Cor 4:7; 1 Cor 1:31; 2 Cor 10:17; Eph 2:9; Rom 2:6; Rom 2:10; Gal 5:6; Pelagius' aquittal at Piospolis, Palestine December 415; Hero and Lazarus, Ep.; Councils of Milevis and Carthage 416; Augustine, Ep. 177; Augustine, Ep. 181; Augustine, Ep. 182; Augustine, Ep. 183; Rom 5:5; Rom 12:3; Ps 59:10; Lk 15:18; New Testament; Eph 3:6-7; Ps 127:1; Ps 121:4; Ps 59:10; Lk 19:10; Rom 4:4-6; Hb 2:4; Rom 1:17; Gal 3:5; Heb 10:38; Rom 11:6; Is 49:8; 2 Cor 6:2; Phil 2:13; Rom 8:28; Rom 9:30-33; Is 28:16; Is 8:14; Rom 10:2-4; 2 Cor 5:21; Rom 5:1; Rom 3:21; 1 Cor 4:7; Ps 59:10; Ps 59:11; 1 Cor 2:12; Rom 5:16; Rom 11:6; Ps 25:10; Eph 2:9; Rom 5:12; 2 Pt 2:16; Rom 9:11-13; Rom 9:13; Mal 1:2-3; Rom 11:5-6; Rom 9:11-12; Rom 9:15; Ex 33:19; Rom 9:16-18; Ex 9:16; Rom 9:17; Rom 9:18; Rom 9:20-21; Is 45:9; Is 29:16; Rom 11:16; Rom 5:12; Rom 9:21; Rom 9:11-12; Rom 5:12; Rom 9:20; Rom 9:20-21; Rom 9:22; Rom 9:23; Rom 8:28-30; Rom 8:30; Rom 11:5-6; Acts 4:32; Rom 9:16; Rom 3:19; 1 Cor 1:31; 2 Cor 10:17; 1 Tm 6:3; Lk 19:10; Mt 18:11; 1 Tm 6:3; Jn 6:49-50; Jn 6:54; Deeds of Pelagius 11. 23; Rom 5:12; Rom 9:24; Jn 1:14; Mt 12:27; Rom 9:27; Is 10:22; Hos 1:10; Rom 11:2; Rom 11:5; Rom 11:6; 1 Cor 15:21-22; The Deeds of Pelagius 11.23-24; The Deeds of Pelagius 33.57; The Deeds of Pelagius 35.65; The Deeds of Pelagius 14.30-31; The Deeds of Pelagius 17.40; The Deeds of Pelagius 35.65; The Deeds of Pelagius18.42; The Deeds of Pelagius 35.65; 1 Tm 6:17-19; Ex 33:19 LXX; Mt 6:12; Lk 11:4; 2 Tm 2:25; Ps. 7:3; Ps 7:4; Ps 9:5; 1 Cor 15:10; Rom 9:16; Ps 127:1; The Grace of Christ and Original Sin 1.8.9; The Grace of Christ and Original Sin 27.28; The Deeds of Pelagius 14.37; Rom 10:2; Rom 10:3; Rom 9:32; Jn 6:66; Rom 10:1-2; Ps 69:30; Gal 5:17; Paulinus Ep. to Severus; Paulinus, Ep. 30.2; Rom 7:4; Lk 19:10; Mt 18:11; Mt 6:13; Lk 11:4; ", "Other Locations Mentioned": "Carthage, Milevis; Jerusalem; Palestine; Africa; Israel" }, { "id": 2186, "name": "letter 186", "lat": 40.926823, "lon": 14.524545, "size": 46518, "year": 416, "color": "red", "date": "416", "person1": "Recipient: Alypius, Augustine", "loc": "Nola", "person2": "Sender: Alypius, Augustine", "loc2": "Hippo Regius", "Correspondent_Clerical_Rank": "bishop", "Ascetic Content": "No", "Other_Personal_Names_Mentioned": "Januarius; Pelagius \"The Briton\"; Pelagius;  Timasius; James (disciple of Pelagius); Innocent; Adam; Moses; Esau; Jacob; Pharaoh; Abraham; Timothy", "Inferred Names": "Paul; The 12 Apostles; Paulinus; David", "Groups": "Pelagians; Jews; Church of Jerusalem; ", "Literary/Historical References": "Gal 2:21; Phil 2:13; Lk 19:10; 1 Cor 4:7; 1 Cor 1:31; 2 Cor 10:17; Eph 2:9; Rom 2:6; Rom 2:10; Gal 5:6; Pelagius' aquittal at Piospolis, Palestine December 415; Hero and Lazarus, Ep.; Councils of Milevis and Carthage 416; Augustine, Ep. 177; Augustine, Ep. 181; Augustine, Ep. 182; Augustine, Ep. 183; Rom 5:5; Rom 12:3; Ps 59:10; Lk 15:18; New Testament; Eph 3:6-7; Ps 127:1; Ps 121:4; Ps 59:10; Lk 19:10; Rom 4:4-6; Hb 2:4; Rom 1:17; Gal 3:5; Heb 10:38; Rom 11:6; Is 49:8; 2 Cor 6:2; Phil 2:13; Rom 8:28; Rom 9:30-33; Is 28:16; Is 8:14; Rom 10:2-4; 2 Cor 5:21; Rom 5:1; Rom 3:21; 1 Cor 4:7; Ps 59:10; Ps 59:11; 1 Cor 2:12; Rom 5:16; Rom 11:6; Ps 25:10; Eph 2:9; Rom 5:12; 2 Pt 2:16; Rom 9:11-13; Rom 9:13; Mal 1:2-3; Rom 11:5-6; Rom 9:11-12; Rom 9:15; Ex 33:19; Rom 9:16-18; Ex 9:16; Rom 9:17; Rom 9:18; Rom 9:20-21; Is 45:9; Is 29:16; Rom 11:16; Rom 5:12; Rom 9:21; Rom 9:11-12; Rom 5:12; Rom 9:20; Rom 9:20-21; Rom 9:22; Rom 9:23; Rom 8:28-30; Rom 8:30; Rom 11:5-6; Acts 4:32; Rom 9:16; Rom 3:19; 1 Cor 1:31; 2 Cor 10:17; 1 Tm 6:3; Lk 19:10; Mt 18:11; 1 Tm 6:3; Jn 6:49-50; Jn 6:54; Deeds of Pelagius 11. 23; Rom 5:12; Rom 9:24; Jn 1:14; Mt 12:27; Rom 9:27; Is 10:22; Hos 1:10; Rom 11:2; Rom 11:5; Rom 11:6; 1 Cor 15:21-22; The Deeds of Pelagius 11.23-24; The Deeds of Pelagius 33.57; The Deeds of Pelagius 35.65; The Deeds of Pelagius 14.30-31; The Deeds of Pelagius 17.40; The Deeds of Pelagius 35.65; The Deeds of Pelagius18.42; The Deeds of Pelagius 35.65; 1 Tm 6:17-19; Ex 33:19 LXX; Mt 6:12; Lk 11:4; 2 Tm 2:25; Ps. 7:3; Ps 7:4; Ps 9:5; 1 Cor 15:10; Rom 9:16; Ps 127:1; The Grace of Christ and Original Sin 1.8.9; The Grace of Christ and Original Sin 27.28; The Deeds of Pelagius 14.37; Rom 10:2; Rom 10:3; Rom 9:32; Jn 6:66; Rom 10:1-2; Ps 69:30; Gal 5:17; Paulinus Ep. to Severus; Paulinus, Ep. 30.2; Rom 7:4; Lk 19:10; Mt 18:11; Mt 6:13; Lk 11:4; ", "Other Locations Mentioned": "Carthage, Milevis; Jerusalem; Palestine; Africa; Israel" },
{ "id": 1187, "name": "letter 187", "lat": 36.882478, "lon": 7.751272, "size": 46571, "year": 417, "color": "blue", "date": "417", "person1": "Sender: Augustine", "loc": "Hippo Regius", "person2": "Recipient: Claudius Postumus Dardanus", "loc2": "Gaul", "Correspondent_Clerical_Rank": "layman", "Ascetic Content": "No", "Other_Personal_Names_Mentioned": "Claudius Postumus Dardanus; Peter; Abraham; Adam; David; Elisha;  Elijah; John; Rebekah; Mary (the mother of Jesus); Abraham; Isaac; Jacob; Solomon; Cornelius; Jeremiah; Caiaphas; Noah; Judah", "Inferred Names": "The 12 disciples; Paul; ", "Groups": "Arians; Apollinarists", "Literary/Historical References": "1 Tm 2:5; Lk23:43; Ps 16:10; Acts 2:27); Lk 16:22; Lk 16:23); Lk 16:22; Lk 16:26; Acts 2:24 ; Wis 8:1; Wis 7:24-25; Jn 10:30 Jn 14:28; Rom 1:3; Jn 1:3; Rom 1:3; Phil 2:7; Jn 3:13; 1 Cor 2:8;  Acts 17:28;  Jer 23:24; Wis 8:1 ; Wis 1:7;  Ps 139:7-8;  1 Cor 6:19; 1 Cor 3:16; Rom 8:9; Mt 6:9;  Rom 1:21; Lk 1:41-44; Lk 1:41;  1 Cor3:16; 1 Cor 2:14 ; Rom 8:24 ; Ti 3:5; Rom 8:24-25; Jn 15:15; Jn 16:12; 1 Cor 15:54; Jn 3:5; Rom 5:12; Jb 7:1; Mt 6:12; Eph 5:26-27; Mt 6:12; Rom 1:21; Rom 1:25; l Cor 13:12; 1 Cor 3:1-2; 1 Cor 3:16; 6:19;  1 Cor 15:46-49; 1 Cor 15:21-22;  Rom 8:3; Rom 5:18; Lk 1:35; Jer 1:5; Mt 1:20; Jn 3:3; Jn 3:5; Heb 11:6; 2 Cor 4:13; Ps 116:10; Rv 10:7; Am 3:7; 1 Cor 15:22;Col 1:13;  Pt 2:5; 2 Cor 6:16; Lv 6:12; Mt 7:22-23; Jn 11:50-52;  Zep 2:11; Ps 29:10; Ps 29:10; Col 2:9; Act 17:24; Jn 2:19; 21; Jn 1:14;  1 Jn 4:16", "Other Locations Mentioned": "Bethlehem" }, { "id": 2187, "name": "letter 187", "lat": 45.57717715, "lon": 2.49095881905, "size": 46571, "year": 417, "color": "red", "date": "417", "person1": "Recipient: Augustine", "loc": "Gaul", "person2": "Sender: Augustine", "loc2": "Hippo Regius", "Correspondent_Clerical_Rank": "layman", "Ascetic Content": "No", "Other_Personal_Names_Mentioned": "Claudius Postumus Dardanus; Peter; Abraham; Adam; David; Elisha;  Elijah; John; Rebekah; Mary (the mother of Jesus); Abraham; Isaac; Jacob; Solomon; Cornelius; Jeremiah; Caiaphas; Noah; Judah", "Inferred Names": "The 12 disciples; Paul; ", "Groups": "Arians; Apollinarists", "Literary/Historical References": "1 Tm 2:5; Lk23:43; Ps 16:10; Acts 2:27); Lk 16:22; Lk 16:23); Lk 16:22; Lk 16:26; Acts 2:24 ; Wis 8:1; Wis 7:24-25; Jn 10:30 Jn 14:28; Rom 1:3; Jn 1:3; Rom 1:3; Phil 2:7; Jn 3:13; 1 Cor 2:8;  Acts 17:28;  Jer 23:24; Wis 8:1 ; Wis 1:7;  Ps 139:7-8;  1 Cor 6:19; 1 Cor 3:16; Rom 8:9; Mt 6:9;  Rom 1:21; Lk 1:41-44;Lk 1:41;  1 Cor3:16; 1 Cor 2:14 ; Rom 8:24 ; Ti 3:5; Rom 8:24-25; Jn 15:15; Jn 16:12; 1 Cor 15:54; Jn 3:5; Rom 5:12; Jb 7:1; Mt 6:12; Eph 5:26-27; Mt 6:12; Rom 1:21; Rom 1:25; l Cor 13:12; 1 Cor 3:1-2; 1 Cor 3:16; 6:19;  1 Cor 15:46-49; 1 Cor 15:21-22;  Rom 8:3; Rom 5:18; Lk 1:35; Jer 1:5; Mt 1:20; Jn 3:3; Jn 3:5; Heb 11:6; 2 Cor 4:13; Ps 116:10; Rv 10:7; Am 3:7; 1 Cor 15:22;Col 1:13;  Pt 2:5; 2 Cor 6:16; Lv 6:12; Mt 7:22-23; Jn 11:50-52;  Zep 2:11; Ps 29:10; Ps 29:10; Col 2:9; Act 17:24; Jn 2:19; 21; Jn 1:14;  1 Jn 4:16 ", "Other Locations Mentioned": "Bethlehem" },
{ "id": 1188, "name": "letter 188", "lat": 36.882478, "lon": 7.751272, "size": 16720, "year": 417, "color": "blue", "date": "417-418", "person1": "Sender: Augustine", "loc": "Hippo Regius", "person2": "Recipient: Juliana", "loc2": "Africa", "Correspondent_Clerical_Rank": "", "Ascetic Content": "Yes", "Other_Personal_Names_Mentioned": "Demetrias; Eve; James;  ", "Inferred Names": "Paul; Juliana; Julina's family; Juliana's daughter; ", "Groups": "", "Literary/Historical References": "Pelagius, Liber ad Demetriadem 11;  1 Thes 2:13;  Rom 5:5; 2 Cor 11:2-3; 2 Cor 4:7; 1 Cor 7:7; Mt 19:11 ; Jas 1:17; Eph 2:8; 2 Cor4:7; 1 Thes 5:17-18; Lk 19:10; Mt 18:11; 1 Cor 4:7; 1 Cor 9-11; Ps 56:12; Ps 30:8;  Phil 2:13; Wis 8:21-22; Wis 8:21-22;  Ps 103:8;  Gal 6:4; Ps 4:4 ; Ps 34:3; Ps 103:5; Wis 8:21;  Gal 5:6; Rom 14:23;  Rom 13:10", "Other Locations Mentioned": "" }, { "id": 2188, "name": "letter 188", "lat": 37.5, "lon": 7.5, "size": 16720, "year": 417, "color": "red", "date": "417-418", "person1": "Recipient: Augustine", "loc": "Africa", "person2": "Sender: Augustine", "loc2": "Hippo Regius", "Correspondent_Clerical_Rank": "", "Ascetic Content": "Yes", "Other_Personal_Names_Mentioned": "Demetrias; Eve; James;  ", "Inferred Names": "Paul; Juliana; Julina's family; Juliana's daughter; ", "Groups": "", "Literary/Historical References": "Pelagius, Liber ad Demetriadem 11;  1 Thes 2:13;  Rom 5:5; 2 Cor 11:2-3; 2 Cor 4:7; 1 Cor 7:7; Mt 19:11 ; Jas 1:17; Eph 2:8; 2 Cor4:7; 1 Thes 5:17-18; Lk 19:10; Mt 18:11; 1 Cor 4:7; 1 Cor 9-11; Ps 56:12; Ps 30:8;  Phil 2:13; Wis 8:21-22; Wis 8:21-22;  Ps 103:8;  Gal 6:4; Ps 4:4 ; Ps 34:3; Ps 103:5; Wis 8:21;  Gal 5:6; Rom 14:23;  Rom 13:10", "Other Locations Mentioned": "" },
{ "id": 1188, "name": "letter 188", "lat": 36.882478, "lon": 7.751272, "size": 16720, "year": 417, "color": "blue", "date": "417-418", "person1": "Sender: Augustine", "loc": "Hippo Regius", "person2": "Recipient: Juliana", "loc2": "Africa", "Correspondent_Clerical_Rank": "", "Ascetic Content": "Yes", "Other_Personal_Names_Mentioned": "Demetrias; Eve; James;  ", "Inferred Names": "Paul; Juliana; Julina's family; Juliana's daughter; ", "Groups": "", "Literary/Historical References": "Pelagius, Liber ad Demetriadem 11;  1 Thes 2:13;  Rom 5:5; 2 Cor 11:2-3; 2 Cor 4:7; 1 Cor 7:7; Mt 19:11 ; Jas 1:17; Eph 2:8; 2 Cor4:7; 1 Thes 5:17-18; Lk 19:10; Mt 18:11; 1 Cor 4:7; 1 Cor 9-11; Ps 56:12; Ps 30:8;  Phil 2:13; Wis 8:21-22; Wis 8:21-22;  Ps 103:8;  Gal 6:4; Ps 4:4 ; Ps 34:3; Ps 103:5; Wis 8:21;  Gal 5:6; Rom 14:23;  Rom 13:10", "Other Locations Mentioned": "" }, { "id": 2188, "name": "letter 188", "lat": 37.5, "lon": 7.5, "size": 16720, "year": 417, "color": "red", "date": "417-418", "person1": "Recipient: Augustine", "loc": "Africa", "person2": "Sender: Augustine", "loc2": "Hippo Regius", "Correspondent_Clerical_Rank": "", "Ascetic Content": "Yes", "Other_Personal_Names_Mentioned": "Demetrias; Eve; James;  ", "Inferred Names": "Paul; Juliana; Julina's family; Juliana's daughter; ", "Groups": "", "Literary/Historical References": "Pelagius, Liber ad Demetriadem 11;  1 Thes 2:13;  Rom 5:5; 2 Cor 11:2-3; 2 Cor 4:7; 1 Cor 7:7; Mt 19:11 ; Jas 1:17; Eph 2:8; 2 Cor4:7; 1 Thes 5:17-18; Lk 19:10; Mt 18:11; 1 Cor 4:7; 1 Cor 9-11; Ps 56:12; Ps 30:8;  Phil 2:13; Wis 8:21-22; Wis 8:21-22;  Ps 103:8;  Gal 6:4; Ps 4:4 ; Ps 34:3; Ps 103:5; Wis 8:21;  Gal 5:6; Rom 14:23;  Rom 13:10", "Other Locations Mentioned": "" },
{ "id": 1189, "name": "letter 189", "lat": 36.882478, "lon": 7.751272, "size": 8207, "year": 417, "color": "blue", "date": "417", "person1": "Sender: Augustine", "loc": "Hippo Regius", "person2": "Recipient: Boniface", "loc2": "Africa", "Correspondent_Clerical_Rank": "layman", "Ascetic Content": "No", "Other_Personal_Names_Mentioned": "Faustus; John; David; Cornelius;  ", "Inferred Names": "Boniface; Paul; ", "Groups": "", "Literary/Historical References": "Mt 22:37;39; Mk 12:30-31; Lk 10:27; Dt 6:5; Lv 19:18; Mt 22:40; Rom 13:10; Gal 5:6; 1 Jn 3:2;Mt 8:8-10; Lk 7:6-9; Mt 11:11 ; Lk 3:3; 1 Cor 7:7; Mt 5:9; Jb 7:1; Mt 6:12; Lk 11:4;", "Other Locations Mentioned": "Israel" }, { "id": 2189, "name": "letter 189", "lat": 37.5, "lon": 7.5, "size": 8207, "year": 417, "color": "red", "date": "417", "person1": "Recipient: Augustine", "loc": "Africa", "person2": "Sender: Augustine", "loc2": "Hippo Regius", "Correspondent_Clerical_Rank": "layman", "Ascetic Content": "No", "Other_Personal_Names_Mentioned": "Faustus; John; David; Cornelius;  ", "Inferred Names": "Boniface; Paul; ", "Groups": "", "Literary/Historical References": "Mt 22:37;39; Mk 12:30-31; Lk 10:27; Dt 6:5; Lv 19:18; Mt 22:40; Rom 13:10; Gal 5:6; 1 Jn 3:2;Mt 8:8-10; Lk 7:6-9; Mt 11:11 ; Lk 3:3; 1 Cor 7:7; Mt 5:9; Jb 7:1; Mt 6:12; Lk 11:4;", "Other Locations Mentioned": "Israel" },
